Metadata-Version: 2.1
Name: Star-Bot-utils
Version: 0.0.1a0
Summary: The main bots utils
Home-page: UNKNOWN
Author: Nite
License: UNKNOWN
Platform: UNKNOWN
Classifier: Intended Audience :: Developers
Classifier: Natural Language :: English
Classifier: Operating System :: OS Independent
Classifier: Programming Language :: Python :: 3.5
Classifier: Programming Language :: Python :: 3.6
Classifier: Programming Language :: Python :: 3.7
Requires-Python: >=3.5.3
